{
  "$schema": "https://developer.microsoft.com/json-schemas/fabric/item/report/definition/visualContainer/2.10.0/schema.json",
  "name": "p2_perfil",
  "position": {
    "x": 851.66666666666674,
    "y": 196.66666666666669,
    "z": 10000,
    "height": 122.5,
    "width": 401.66666666666669,
    "tabOrder": 10000
  },
  "visual": {
    "visualType": "tableEx",
    "query": {
      "queryState": {
        "Values": {
          "projections": [
            {
              "field": {
                "Column": {
                  "Expression": {
                    "SourceRef": {
                      "Entity": "fact_orders"
                    }
                  },
                  "Property": "situacao_entrega"
                }
              },
              "queryRef": "fact_orders.situacao_entrega",
              "nativeQueryRef": "Status",
              "displayName": "Status"
            },
            {
              "field": {
                "Measure": {
                  "Expression": {
                    "SourceRef": {
                      "Entity": "_Medidas"
                    }
                  },
                  "Property": "Ticket Médio"
                }
              },
              "queryRef": "_Medidas.Ticket Médio",
              "nativeQueryRef": "Ticket",
              "displayName": "Ticket"
            },
            {
              "field": {
                "Measure": {
                  "Expression": {
                    "SourceRef": {
                      "Entity": "_Medidas"
                    }
                  },
                  "Property": "Frete Médio"
                }
              },
              "queryRef": "_Medidas.Frete Médio",
              "nativeQueryRef": "Frete",
              "displayName": "Frete"
            },
            {
              "field": {
                "Measure": {
                  "Expression": {
                    "SourceRef": {
                      "Entity": "_Medidas"
                    }
                  },
                  "Property": "Itens Médio"
                }
              },
              "queryRef": "_Medidas.Itens Médio",
              "nativeQueryRef": "Itens",
              "displayName": "Itens"
            },
            {
              "field": {
                "Measure": {
                  "Expression": {
                    "SourceRef": {
                      "Entity": "_Medidas"
                    }
                  },
                  "Property": "Parcelas Média"
                }
              },
              "queryRef": "_Medidas.Parcelas Média",
              "nativeQueryRef": "Parcelas",
              "displayName": "Parcelas"
            },
            {
              "field": {
                "Measure": {
                  "Expression": {
                    "SourceRef": {
                      "Entity": "_Medidas"
                    }
                  },
                  "Property": "Lead Time Médio"
                }
              },
              "queryRef": "_Medidas.Lead Time Médio",
              "nativeQueryRef": "Lead",
              "displayName": "Lead"
            }
          ]
        }
      }
    },
    "objects": {
      "columnWidth": [
        {
          "properties": {
            "value": {
              "expr": {
                "Literal": {
                  "Value": "78.41381074756009D"
                }
              }
            }
          },
          "selector": {
            "metadata": "fact_orders.situacao_entrega"
          }
        }
      ],
      "columnHeaders": [
        {
          "properties": {}
        }
      ]
    },
    "visualContainerObjects": {
      "title": [
        {
          "properties": {
            "show": {
              "expr": {
                "Literal": {
                  "Value": "true"
                }
              }
            },
            "text": {
              "expr": {
                "Literal": {
                  "Value": "'Perfil: atrasado vs no prazo'"
                }
              }
            }
          }
        }
      ]
    },
    "drillFilterOtherVisuals": true
  }
}